markdown_edit.py
markdown_editor/__init__.py
markdown_editor/editor.py
markdown_editor/markdown_edit.tpl
markdown_editor/terminal_edit.py
markdown_editor/web_edit.py
markdown_editor/css/markdown.css
markdown_editor/css/markdown_edit.css
markdown_editor/css/pygments.css
markdown_editor/js/markdown_edit.js
markdown_editor/libs/bootstrap-3.1.1-dist/css/bootstrap-theme.css
markdown_editor/libs/bootstrap-3.1.1-dist/css/bootstrap-theme.css.map
markdown_editor/libs/bootstrap-3.1.1-dist/css/bootstrap-theme.min.css
markdown_editor/libs/bootstrap-3.1.1-dist/css/bootstrap.css
markdown_editor/libs/bootstrap-3.1.1-dist/css/bootstrap.css.map
markdown_editor/libs/bootstrap-3.1.1-dist/css/bootstrap.min.css
markdown_editor/libs/bootstrap-3.1.1-dist/fonts/glyphicons-halflings-regular.eot
markdown_editor/libs/bootstrap-3.1.1-dist/fonts/glyphicons-halflings-regular.svg
markdown_editor/libs/bootstrap-3.1.1-dist/fonts/glyphicons-halflings-regular.ttf
markdown_editor/libs/bootstrap-3.1.1-dist/fonts/glyphicons-halflings-regular.woff
markdown_editor/libs/bootstrap-3.1.1-dist/js/bootstrap.js
markdown_editor/libs/bootstrap-3.1.1-dist/js/bootstrap.min.js
markdown_editor/libs/codemirror-5.15.2/codemirror.css
markdown_editor/libs/codemirror-5.15.2/codemirror.js
markdown_editor/libs/codemirror-5.15.2/addon/dialog/dialog.css
markdown_editor/libs/codemirror-5.15.2/addon/dialog/dialog.js
markdown_editor/libs/codemirror-5.15.2/keymap/emacs.js
markdown_editor/libs/codemirror-5.15.2/keymap/sublime.js
markdown_editor/libs/codemirror-5.15.2/keymap/vim.js
markdown_editor/libs/codemirror-5.15.2/mode/markdown.js
markdown_editor/libs/codemirror-5.15.2/theme/3024-night.css
markdown_editor/libs/codemirror-5.15.2/theme/neat.css
markdown_editor/libs/jquery-1.11.0-dist/jquery-1.11.0.js
markdown_editor/libs/jquery-1.11.0-dist/jquery-1.11.0.min.js
markdown_editor/libs/jquery-1.11.0-dist/jquery-1.11.0.min.map
Markdown_Editor-1.0.4.dist-info/METADATA
Markdown_Editor-1.0.4.dist-info/WHEEL
Markdown_Editor-1.0.4.dist-info/entry_points.txt
Markdown_Editor-1.0.4.dist-info/top_level.txt
Markdown_Editor-1.0.4.dist-info/RECORD
