Metadata-Version: 2.1
Name: Markdown-Editor
Version: 1.0.4
Summary: Standalone editor for your markdown files
Home-page: https://github.com/ncornette/Python-Markdown-Editor.git
Author: Nicolas Cornette
Author-email: nicolas.cornette@gmail.com
License: UNKNOWN
Platform: UNKNOWN
Classifier: Development Status :: 5 - Production/Stable
Classifier: Intended Audience :: Developers
Classifier: Topic :: Software Development :: Build Tools
Classifier: License :: OSI Approved :: MIT License
Classifier: Programming Language :: Python :: 2
Classifier: Programming Language :: Python :: 2.7
Classifier: Programming Language :: Python :: 3
Classifier: Programming Language :: Python :: 3.5
Classifier: Programming Language :: Python :: 3.6
Classifier: Programming Language :: Python :: 3.7
Requires-Dist: Markdown
Requires-Dist: Pygments
Requires-Dist: bottle
Requires-Dist: pymdown-extensions (>=2.0)
